betterneural/__init__.py
betterneural/networks.py
betterNeural-0.0.5.dist-info/METADATA
betterNeural-0.0.5.dist-info/WHEEL
betterNeural-0.0.5.dist-info/top_level.txt
betterNeural-0.0.5.dist-info/RECORD
