Metadata-Version: 2.1
Name: betterNeural
Version: 0.0.5
Summary: A package with tools for Neural networks
Home-page: https://github.com/riioze/betterneural
Author: riioze
Author-email: riioze0@gmail.com
License: UNKNOWN
Platform: UNKNOWN
Classifier: Programming Language :: Python :: 3
Classifier: License :: OSI Approved :: MIT License
Classifier: Operating System :: OS Independent
Requires-Python: >=3.6
Requires-Dist: numpy
